guara/__init__.py
guara/abstract_transaction.py
guara/assertion.py
guara/it.py
guara/setup.py
guara/transaction.py
guara/utils.py
guara/asynchronous/__init__.py
guara/asynchronous/abstract_transaction.py
guara/asynchronous/assertion.py
guara/asynchronous/it.py
guara/asynchronous/setup.py
guara/asynchronous/transaction.py
guara-0.0.14.dist-info/METADATA
guara-0.0.14.dist-info/WHEEL
guara-0.0.14.dist-info/licenses/LICENSE
guara-0.0.14.dist-info/RECORD
