Metadata-Version: 2.4
Name: guara
Version: 0.0.14
Summary: Framework to build UI test automation in Page Transactions pattern
Project-URL: Homepage, https://github.com/douglasdcm/guara
Project-URL: Bug Tracker, https://github.com/douglasdcm/guara/issues
Author-email: Douglas Cardoso <noemail@noemail.com>
License-File: LICENSE
Classifier: Development Status :: 4 - Beta
Classifier: License :: OSI Approved :: MIT License
Classifier: Operating System :: OS Independent
Classifier: Programming Language :: Python :: 3
Requires-Python: >=3.8
Requires-Dist: python-dotenv
